{"status": 0, "info": "", "data": {"GE": [{"Model Name": "model3", "Model ID": 1, "Data Index": 0, "Request ID": 0, "Duration Type": "input", "Start": 1601880380.8744795, "End": 1601880380.8745215}, {"Model Name": "model3", "Model ID": 1, "Data Index": 0, "Request ID": 0, "Duration Type": "infer", "Start": 1601880380.874523, "End": 1601880380.9032443}, {"Model Name": "model3", "Model ID": 1, "Data Index": 0, "Request ID": 0, "Duration Type": "output", "Start": 1601880380.903247, "End": 1601880380.9032512}, {"Model Name": "model3", "Model ID": 1, "Data Index": 0, "Request ID": 0, "Duration Type": "input", "Start": 1601880381.0023954, "End": 1601880381.002476}, {"Model Name": "model3", "Model ID": 1, "Data Index": 0, "Request ID": 0, "Duration Type": "infer", "Start": 1601880381.0024774, "End": 1601880381.0311856}, {"Model Name": "model3", "Model ID": 1, "Data Index": 0, "Request ID": 0, "Duration Type": "output", "Start": 1601880381.0311875, "End": 1601880381.0311904}, {"Model Name": "model3", "Model ID": 1, "Data Index": 0, "Request ID": 0, "Duration Type": "input", "Start": 1601880381.099204, "End": 1601880381.0992856}, {"Model Name": "model3", "Model ID": 1, "Data Index": 0, "Request ID": 0, "Duration Type": "infer", "Start": 1601880381.099287, "End": 1601880381.1280594}, {"Model Name": "model3", "Model ID": 1, "Data Index": 0, "Request ID": 0, "Duration Type": "output", "Start": 1601880381.1280615, "End": 1601880381.1280649}, {"Model Name": "model3", "Model ID": 1, "Data Index": 0, "Request ID": 0, "Duration Type": "input", "Start": 1601880381.2000597, "End": 1601880381.2001374}, {"Model Name": "model3", "Model ID": 1, "Data Index": 0, "Request ID": 0, "Duration Type": "infer", "Start": 1601880381.2001388, "End": 1601880381.2288554}, {"Model Name": "model3", "Model ID": 1, "Data Index": 0, "Request ID": 0, "Duration Type": "output", "Start": 1601880381.2288578, "End": 1601880381.2288609}, {"Model Name": "model3", "Model ID": 1, "Data Index": 0, "Request ID": 0, "Duration Type": "input", "Start": 1601880381.29526, "End": 1601880381.2953358}, {"Model Name": "model3", "Model ID": 1, "Data Index": 0, "Request ID": 0, "Duration Type": "infer", "Start": 1601880381.2953372, "End": 1601880381.323951}, {"Model Name": "model3", "Model ID": 1, "Data Index": 0, "Request ID": 0, "Duration Type": "output", "Start": 1601880381.3239532, "End": 1601880381.3239563}, {"Model Name": "model3", "Model ID": 1, "Data Index": 0, "Request ID": 0, "Duration Type": "input", "Start": 1601880381.3840978, "End": 1601880381.3841698}, {"Model Name": "model3", "Model ID": 1, "Data Index": 0, "Request ID": 0, "Duration Type": "infer", "Start": 1601880381.3841712, "End": 1601880381.4128685}, {"Model Name": "model3", "Model ID": 1, "Data Index": 0, "Request ID": 0, "Duration Type": "output", "Start": 1601880381.4128711, "End": 1601880381.4128745}, {"Model Name": "model3", "Model ID": 1, "Data Index": 0, "Request ID": 0, "Duration Type": "input", "Start": 1601880381.4804018, "End": 1601880381.4804802}, {"Model Name": "model3", "Model ID": 1, "Data Index": 0, "Request ID": 0, "Duration Type": "infer", "Start": 1601880381.4804816, "End": 1601880381.5091217}, {"Model Name": "model3", "Model ID": 1, "Data Index": 0, "Request ID": 0, "Duration Type": "output", "Start": 1601880381.509124, "End": 1601880381.509127}, {"Model Name": "model3", "Model ID": 1, "Data Index": 0, "Request ID": 0, "Duration Type": "input", "Start": 1601880381.5779269, "End": 1601880381.578004}, {"Model Name": "model3", "Model ID": 1, "Data Index": 0, "Request ID": 0, "Duration Type": "infer", "Start": 1601880381.5780053, "End": 1601880381.6067371}, {"Model Name": "model3", "Model ID": 1, "Data Index": 0, "Request ID": 0, "Duration Type": "output", "Start": 1601880381.6067395, "End": 1601880381.6067429}, {"Model Name": "model3", "Model ID": 1, "Data Index": 0, "Request ID": 0, "Duration Type": "input", "Start": 1601880381.6742961, "End": 1601880381.674375}, {"Model Name": "model3", "Model ID": 1, "Data Index": 0, "Request ID": 0, "Duration Type": "infer", "Start": 1601880381.6743765, "End": 1601880381.7030945}, {"Model Name": "model3", "Model ID": 1, "Data Index": 0, "Request ID": 0, "Duration Type": "output", "Start": 1601880381.7030966, "End": 1601880381.7031}, {"Model Name": "model3", "Model ID": 1, "Data Index": 0, "Request ID": 0, "Duration Type": "input", "Start": 1601880381.7693806, "End": 1601880381.7694607}, {"Model Name": "model3", "Model ID": 1, "Data Index": 0, "Request ID": 0, "Duration Type": "infer", "Start": 1601880381.769462, "End": 1601880381.7981663}, {"Model Name": "model3", "Model ID": 1, "Data Index": 0, "Request ID": 0, "Duration Type": "output", "Start": 1601880381.7981687, "End": 1601880381.7981715}, {"Model Name": "model3", "Model ID": 1, "Data Index": 0, "Request ID": 0, "Duration Type": "input", "Start": 1601880381.8661542, "End": 1601880381.8662312}, {"Model Name": "model3", "Model ID": 1, "Data Index": 0, "Request ID": 0, "Duration Type": "infer", "Start": 1601880381.8662326, "End": 1601880381.8949044}, {"Model Name": "model3", "Model ID": 1, "Data Index": 0, "Request ID": 0, "Duration Type": "output", "Start": 1601880381.894907, "End": 1601880381.8949113}, {"Model Name": "model3", "Model ID": 1, "Data Index": 0, "Request ID": 0, "Duration Type": "input", "Start": 1601880381.9623816, "End": 1601880381.9624572}, {"Model Name": "model3", "Model ID": 1, "Data Index": 0, "Request ID": 0, "Duration Type": "infer", "Start": 1601880381.9624586, "End": 1601880381.9911098}, {"Model Name": "model3", "Model ID": 1, "Data Index": 0, "Request ID": 0, "Duration Type": "output", "Start": 1601880381.991112, "End": 1601880381.9911149}, {"Model Name": "model3", "Model ID": 1, "Data Index": 0, "Request ID": 0, "Duration Type": "input", "Start": 1601880382.0584378, "End": 1601880382.0585153}, {"Model Name": "model3", "Model ID": 1, "Data Index": 0, "Request ID": 0, "Duration Type": "infer", "Start": 1601880382.0585167, "End": 1601880382.0871625}, {"Model Name": "model3", "Model ID": 1, "Data Index": 0, "Request ID": 0, "Duration Type": "output", "Start": 1601880382.0871644, "End": 1601880382.087168}, {"Model Name": "model3", "Model ID": 1, "Data Index": 0, "Request ID": 0, "Duration Type": "input", "Start": 1601880382.1548567, "End": 1601880382.1549342}, {"Model Name": "model3", "Model ID": 1, "Data Index": 0, "Request ID": 0, "Duration Type": "infer", "Start": 1601880382.1549356, "End": 1601880382.1836138}, {"Model Name": "model3", "Model ID": 1, "Data Index": 0, "Request ID": 0, "Duration Type": "output", "Start": 1601880382.1836157, "End": 1601880382.1836193}, {"Model Name": "model3", "Model ID": 1, "Data Index": 0, "Request ID": 0, "Duration Type": "input", "Start": 1601880382.250601, "End": 1601880382.2506778}, {"Model Name": "model3", "Model ID": 1, "Data Index": 0, "Request ID": 0, "Duration Type": "infer", "Start": 1601880382.2506793, "End": 1601880382.2794154}, {"Model Name": "model3", "Model ID": 1, "Data Index": 0, "Request ID": 0, "Duration Type": "output", "Start": 1601880382.2794173, "End": 1601880382.2794201}, {"Model Name": "model3", "Model ID": 1, "Data Index": 0, "Request ID": 0, "Duration Type": "input", "Start": 1601880382.347753, "End": 1601880382.3478298}, {"Model Name": "model3", "Model ID": 1, "Data Index": 0, "Request ID": 0, "Duration Type": "infer", "Start": 1601880382.3478312, "End": 1601880382.3765645}, {"Model Name": "model3", "Model ID": 1, "Data Index": 0, "Request ID": 0, "Duration Type": "output", "Start": 1601880382.3765666, "End": 1601880382.3765695}, {"Model Name": "model3", "Model ID": 1, "Data Index": 0, "Request ID": 0, "Duration Type": "input", "Start": 1601880382.4420729, "End": 1601880382.4421465}, {"Model Name": "model3", "Model ID": 1, "Data Index": 0, "Request ID": 0, "Duration Type": "infer", "Start": 1601880382.442148, "End": 1601880382.4708023}, {"Model Name": "model3", "Model ID": 1, "Data Index": 0, "Request ID": 0, "Duration Type": "output", "Start": 1601880382.4708045, "End": 1601880382.470808}, {"Model Name": "model3", "Model ID": 1, "Data Index": 0, "Request ID": 0, "Duration Type": "input", "Start": 1601880382.5392504, "End": 1601880382.5393283}, {"Model Name": "model3", "Model ID": 1, "Data Index": 0, "Request ID": 0, "Duration Type": "infer", "Start": 1601880382.5393298, "End": 1601880382.5680082}, {"Model Name": "model3", "Model ID": 1, "Data Index": 0, "Request ID": 0, "Duration Type": "output", "Start": 1601880382.5680108, "End": 1601880382.568014}, {"Model Name": "model3", "Model ID": 1, "Data Index": 0, "Request ID": 0, "Duration Type": "input", "Start": 1601880382.638174, "End": 1601880382.6382473}, {"Model Name": "model3", "Model ID": 1, "Data Index": 0, "Request ID": 0, "Duration Type": "infer", "Start": 1601880382.6382487, "End": 1601880382.667046}, {"Model Name": "model3", "Model ID": 1, "Data Index": 0, "Request ID": 0, "Duration Type": "output", "Start": 1601880382.6670485, "End": 1601880382.667101}, {"Model Name": "model3", "Model ID": 1, "Data Index": 0, "Request ID": 0, "Duration Type": "input", "Start": 1601880382.7359939, "End": 1601880382.7360728}, {"Model Name": "model3", "Model ID": 1, "Data Index": 0, "Request ID": 0, "Duration Type": "infer", "Start": 1601880382.7360742, "End": 1601880382.764807}, {"Model Name": "model3", "Model ID": 1, "Data Index": 0, "Request ID": 0, "Duration Type": "output", "Start": 1601880382.764858, "End": 1601880382.7648613}, {"Model Name": "model3", "Model ID": 1, "Data Index": 0, "Request ID": 0, "Duration Type": "input", "Start": 1601880382.831322, "End": 1601880382.8314006}, {"Model Name": "model3", "Model ID": 1, "Data Index": 0, "Request ID": 0, "Duration Type": "infer", "Start": 1601880382.8314018, "End": 1601880382.8602324}, {"Model Name": "model3", "Model ID": 1, "Data Index": 0, "Request ID": 0, "Duration Type": "output", "Start": 1601880382.8602347, "End": 1601880382.8602383}, {"Model Name": "model3", "Model ID": 1, "Data Index": 0, "Request ID": 0, "Duration Type": "input", "Start": 1601880382.9268339, "End": 1601880382.9269114}, {"Model Name": "model3", "Model ID": 1, "Data Index": 0, "Request ID": 0, "Duration Type": "infer", "Start": 1601880382.9269128, "End": 1601880382.9556463}, {"Model Name": "model3", "Model ID": 1, "Data Index": 0, "Request ID": 0, "Duration Type": "output", "Start": 1601880382.9556966, "End": 1601880382.9557002}, {"Model Name": "model3", "Model ID": 1, "Data Index": 0, "Request ID": 0, "Duration Type": "input", "Start": 1601880383.0232744, "End": 1601880383.023352}, {"Model Name": "model3", "Model ID": 1, "Data Index": 0, "Request ID": 0, "Duration Type": "infer", "Start": 1601880383.0233533, "End": 1601880383.052041}, {"Model Name": "model3", "Model ID": 1, "Data Index": 0, "Request ID": 0, "Duration Type": "output", "Start": 1601880383.0520432, "End": 1601880383.0520952}, {"Model Name": "model3", "Model ID": 1, "Data Index": 0, "Request ID": 0, "Duration Type": "input", "Start": 1601880383.1212807, "End": 1601880383.1213596}, {"Model Name": "model3", "Model ID": 1, "Data Index": 0, "Request ID": 0, "Duration Type": "infer", "Start": 1601880383.1213608, "End": 1601880383.1501143}, {"Model Name": "model3", "Model ID": 1, "Data Index": 0, "Request ID": 0, "Duration Type": "output", "Start": 1601880383.1501644, "End": 1601880383.1501677}, {"Model Name": "model3", "Model ID": 1, "Data Index": 0, "Request ID": 0, "Duration Type": "input", "Start": 1601880383.2176254, "End": 1601880383.217703}, {"Model Name": "model3", "Model ID": 1, "Data Index": 0, "Request ID": 0, "Duration Type": "infer", "Start": 1601880383.2177045, "End": 1601880383.2464857}, {"Model Name": "model3", "Model ID": 1, "Data Index": 0, "Request ID": 0, "Duration Type": "output", "Start": 1601880383.2465355, "End": 1601880383.2465384}, {"Model Name": "model3", "Model ID": 1, "Data Index": 0, "Request ID": 0, "Duration Type": "input", "Start": 1601880383.3135133, "End": 1601880383.3135917}, {"Model Name": "model3", "Model ID": 1, "Data Index": 0, "Request ID": 0, "Duration Type": "infer", "Start": 1601880383.3135931, "End": 1601880383.342372}, {"Model Name": "model3", "Model ID": 1, "Data Index": 0, "Request ID": 0, "Duration Type": "output", "Start": 1601880383.342374, "End": 1601880383.342378}, {"Model Name": "model3", "Model ID": 1, "Data Index": 0, "Request ID": 0, "Duration Type": "input", "Start": 1601880383.4102714, "End": 1601880383.4103436}, {"Model Name": "model3", "Model ID": 1, "Data Index": 0, "Request ID": 0, "Duration Type": "infer", "Start": 1601880383.410345, "End": 1601880383.4392362}, {"Model Name": "model3", "Model ID": 1, "Data Index": 0, "Request ID": 0, "Duration Type": "output", "Start": 1601880383.4392383, "End": 1601880383.4392416}, {"Model Name": "model3", "Model ID": 1, "Data Index": 0, "Request ID": 0, "Duration Type": "input", "Start": 1601880383.5083487, "End": 1601880383.5084229}, {"Model Name": "model3", "Model ID": 1, "Data Index": 0, "Request ID": 0, "Duration Type": "infer", "Start": 1601880383.5084243, "End": 1601880383.5371199}, {"Model Name": "model3", "Model ID": 1, "Data Index": 0, "Request ID": 0, "Duration Type": "output", "Start": 1601880383.537123, "End": 1601880383.537126}, {"Model Name": "model3", "Model ID": 1, "Data Index": 0, "Request ID": 0, "Duration Type": "input", "Start": 1601880383.6035807, "End": 1601880383.6036587}, {"Model Name": "model3", "Model ID": 1, "Data Index": 0, "Request ID": 0, "Duration Type": "infer", "Start": 1601880383.60366, "End": 1601880383.632364}, {"Model Name": "model3", "Model ID": 1, "Data Index": 0, "Request ID": 0, "Duration Type": "output", "Start": 1601880383.6323662, "End": 1601880383.632369}, {"Model Name": "model3", "Model ID": 1, "Data Index": 0, "Request ID": 0, "Duration Type": "input", "Start": 1601880383.6984096, "End": 1601880383.6984856}, {"Model Name": "model3", "Model ID": 1, "Data Index": 0, "Request ID": 0, "Duration Type": "infer", "Start": 1601880383.698487, "End": 1601880383.7271454}, {"Model Name": "model3", "Model ID": 1, "Data Index": 0, "Request ID": 0, "Duration Type": "output", "Start": 1601880383.7271476, "End": 1601880383.7271507}, {"Model Name": "model3", "Model ID": 1, "Data Index": 0, "Request ID": 0, "Duration Type": "input", "Start": 1601880383.794269, "End": 1601880383.7943473}, {"Model Name": "model3", "Model ID": 1, "Data Index": 0, "Request ID": 0, "Duration Type": "infer", "Start": 1601880383.794349, "End": 1601880383.8230808}, {"Model Name": "model3", "Model ID": 1, "Data Index": 0, "Request ID": 0, "Duration Type": "output", "Start": 1601880383.8230832, "End": 1601880383.8230867}, {"Model Name": "model3", "Model ID": 1, "Data Index": 0, "Request ID": 0, "Duration Type": "input", "Start": 1601880383.8900003, "End": 1601880383.8900757}, {"Model Name": "model3", "Model ID": 1, "Data Index": 0, "Request ID": 0, "Duration Type": "infer", "Start": 1601880383.8900769, "End": 1601880383.9187415}, {"Model Name": "model3", "Model ID": 1, "Data Index": 0, "Request ID": 0, "Duration Type": "output", "Start": 1601880383.9187438, "End": 1601880383.9187467}, {"Model Name": "model3", "Model ID": 1, "Data Index": 0, "Request ID": 0, "Duration Type": "input", "Start": 1601880384.1757936, "End": 1601880384.1758711}, {"Model Name": "model3", "Model ID": 1, "Data Index": 0, "Request ID": 0, "Duration Type": "infer", "Start": 1601880384.1758726, "End": 1601880384.2045233}, {"Model Name": "model3", "Model ID": 1, "Data Index": 0, "Request ID": 0, "Duration Type": "output", "Start": 1601880384.204526, "End": 1601880384.2045288}, {"Model Name": "model3", "Model ID": 1, "Data Index": 0, "Request ID": 0, "Duration Type": "input", "Start": 1601880384.2751453, "End": 1601880384.2752206}, {"Model Name": "model3", "Model ID": 1, "Data Index": 0, "Request ID": 0, "Duration Type": "infer", "Start": 1601880384.275222, "End": 1601880384.30389}, {"Model Name": "model3", "Model ID": 1, "Data Index": 0, "Request ID": 0, "Duration Type": "output", "Start": 1601880384.3038921, "End": 1601880384.3038955}, {"Model Name": "model3", "Model ID": 1, "Data Index": 0, "Request ID": 0, "Duration Type": "input", "Start": 1601880384.3708277, "End": 1601880384.3709037}, {"Model Name": "model3", "Model ID": 1, "Data Index": 0, "Request ID": 0, "Duration Type": "infer", "Start": 1601880384.3709052, "End": 1601880384.4005497}, {"Model Name": "model3", "Model ID": 1, "Data Index": 0, "Request ID": 0, "Duration Type": "output", "Start": 1601880384.400552, "End": 1601880384.4005554}, {"Model Name": "model3", "Model ID": 1, "Data Index": 0, "Request ID": 0, "Duration Type": "input", "Start": 1601880384.4689567, "End": 1601880384.4690344}, {"Model Name": "model3", "Model ID": 1, "Data Index": 0, "Request ID": 0, "Duration Type": "infer", "Start": 1601880384.4690356, "End": 1601880384.497737}, {"Model Name": "model3", "Model ID": 1, "Data Index": 0, "Request ID": 0, "Duration Type": "output", "Start": 1601880384.4977388, "End": 1601880384.497742}, {"Model Name": "model3", "Model ID": 1, "Data Index": 0, "Request ID": 0, "Duration Type": "input", "Start": 1601880384.5652268, "End": 1601880384.5653055}, {"Model Name": "model3", "Model ID": 1, "Data Index": 0, "Request ID": 0, "Duration Type": "infer", "Start": 1601880384.565307, "End": 1601880384.5940297}, {"Model Name": "model3", "Model ID": 1, "Data Index": 0, "Request ID": 0, "Duration Type": "output", "Start": 1601880384.5940316, "End": 1601880384.5940354}, {"Model Name": "model3", "Model ID": 1, "Data Index": 0, "Request ID": 0, "Duration Type": "input", "Start": 1601880384.6641464, "End": 1601880384.6642237}, {"Model Name": "model3", "Model ID": 1, "Data Index": 0, "Request ID": 0, "Duration Type": "infer", "Start": 1601880384.664225, "End": 1601880384.692909}, {"Model Name": "model3", "Model ID": 1, "Data Index": 0, "Request ID": 0, "Duration Type": "output", "Start": 1601880384.6929116, "End": 1601880384.6929147}, {"Model Name": "model3", "Model ID": 1, "Data Index": 0, "Request ID": 0, "Duration Type": "input", "Start": 1601880384.760327, "End": 1601880384.7604053}, {"Model Name": "model3", "Model ID": 1, "Data Index": 0, "Request ID": 0, "Duration Type": "infer", "Start": 1601880384.7604067, "End": 1601880384.7891037}, {"Model Name": "model3", "Model ID": 1, "Data Index": 0, "Request ID": 0, "Duration Type": "output", "Start": 1601880384.789106, "End": 1601880384.7891095}, {"Model Name": "model3", "Model ID": 1, "Data Index": 0, "Request ID": 0, "Duration Type": "input", "Start": 1601880384.8547535, "End": 1601880384.854831}, {"Model Name": "model3", "Model ID": 1, "Data Index": 0, "Request ID": 0, "Duration Type": "infer", "Start": 1601880384.8548324, "End": 1601880384.8834894}, {"Model Name": "model3", "Model ID": 1, "Data Index": 0, "Request ID": 0, "Duration Type": "output", "Start": 1601880384.8834915, "End": 1601880384.8834944}, {"Model Name": "model3", "Model ID": 1, "Data Index": 0, "Request ID": 0, "Duration Type": "input", "Start": 1601880384.952196, "End": 1601880384.9522738}, {"Model Name": "model3", "Model ID": 1, "Data Index": 0, "Request ID": 0, "Duration Type": "infer", "Start": 1601880384.9522753, "End": 1601880384.9810123}, {"Model Name": "model3", "Model ID": 1, "Data Index": 0, "Request ID": 0, "Duration Type": "output", "Start": 1601880384.9810147, "End": 1601880384.981018}, {"Model Name": "model3", "Model ID": 1, "Data Index": 0, "Request ID": 0, "Duration Type": "input", "Start": 1601880385.0488617, "End": 1601880385.048943}, {"Model Name": "model3", "Model ID": 1, "Data Index": 0, "Request ID": 0, "Duration Type": "infer", "Start": 1601880385.0489445, "End": 1601880385.077605}, {"Model Name": "model3", "Model ID": 1, "Data Index": 0, "Request ID": 0, "Duration Type": "output", "Start": 1601880385.0776072, "End": 1601880385.0776107}, {"Model Name": "model3", "Model ID": 1, "Data Index": 0, "Request ID": 0, "Duration Type": "input", "Start": 1601880385.1465425, "End": 1601880385.1466162}, {"Model Name": "model3", "Model ID": 1, "Data Index": 0, "Request ID": 0, "Duration Type": "infer", "Start": 1601880385.1466177, "End": 1601880385.1753116}, {"Model Name": "model3", "Model ID": 1, "Data Index": 0, "Request ID": 0, "Duration Type": "output", "Start": 1601880385.1753135, "End": 1601880385.1753163}, {"Model Name": "model3", "Model ID": 1, "Data Index": 0, "Request ID": 0, "Duration Type": "input", "Start": 1601880385.2432263, "End": 1601880385.2433023}, {"Model Name": "model3", "Model ID": 1, "Data Index": 0, "Request ID": 0, "Duration Type": "infer", "Start": 1601880385.2433038, "End": 1601880385.27201}, {"Model Name": "model3", "Model ID": 1, "Data Index": 0, "Request ID": 0, "Duration Type": "output", "Start": 1601880385.2720122, "End": 1601880385.2720156}, {"Model Name": "model3", "Model ID": 1, "Data Index": 0, "Request ID": 0, "Duration Type": "input", "Start": 1601880385.3405523, "End": 1601880385.340629}, {"Model Name": "model3", "Model ID": 1, "Data Index": 0, "Request ID": 0, "Duration Type": "infer", "Start": 1601880385.3406305, "End": 1601880385.3693519}, {"Model Name": "model3", "Model ID": 1, "Data Index": 0, "Request ID": 0, "Duration Type": "output", "Start": 1601880385.369354, "End": 1601880385.3693578}, {"Model Name": "model3", "Model ID": 1, "Data Index": 0, "Request ID": 0, "Duration Type": "input", "Start": 1601880385.4399173, "End": 1601880385.439991}, {"Model Name": "model3", "Model ID": 1, "Data Index": 0, "Request ID": 0, "Duration Type": "infer", "Start": 1601880385.4399924, "End": 1601880385.4688191}, {"Model Name": "model3", "Model ID": 1, "Data Index": 0, "Request ID": 0, "Duration Type": "output", "Start": 1601880385.4688215, "End": 1601880385.468825}, {"Model Name": "model3", "Model ID": 1, "Data Index": 0, "Request ID": 0, "Duration Type": "input", "Start": 1601880385.5363913, "End": 1601880385.5364683}, {"Model Name": "model3", "Model ID": 1, "Data Index": 0, "Request ID": 0, "Duration Type": "infer", "Start": 1601880385.5364697, "End": 1601880385.5651982}, {"Model Name": "model3", "Model ID": 1, "Data Index": 0, "Request ID": 0, "Duration Type": "output", "Start": 1601880385.5652003, "End": 1601880385.565204}, {"Model Name": "model3", "Model ID": 1, "Data Index": 0, "Request ID": 0, "Duration Type": "input", "Start": 1601880385.6308289, "End": 1601880385.6309066}, {"Model Name": "model3", "Model ID": 1, "Data Index": 0, "Request ID": 0, "Duration Type": "infer", "Start": 1601880385.630908, "End": 1601880385.6597407}, {"Model Name": "model3", "Model ID": 1, "Data Index": 0, "Request ID": 0, "Duration Type": "output", "Start": 1601880385.6597435, "End": 1601880385.6597471}, {"Model Name": "model3", "Model ID": 1, "Data Index": 0, "Request ID": 0, "Duration Type": "input", "Start": 1601880385.7268775, "End": 1601880385.726955}, {"Model Name": "model3", "Model ID": 1, "Data Index": 0, "Request ID": 0, "Duration Type": "infer", "Start": 1601880385.7269564, "End": 1601880385.7556412}, {"Model Name": "model3", "Model ID": 1, "Data Index": 0, "Request ID": 0, "Duration Type": "output", "Start": 1601880385.7556431, "End": 1601880385.7556472}, {"Model Name": "model3", "Model ID": 1, "Data Index": 0, "Request ID": 0, "Duration Type": "input", "Start": 1601880385.8233624, "End": 1601880385.8234413}, {"Model Name": "model3", "Model ID": 1, "Data Index": 0, "Request ID": 0, "Duration Type": "infer", "Start": 1601880385.8234427, "End": 1601880385.8522904}, {"Model Name": "model3", "Model ID": 1, "Data Index": 0, "Request ID": 0, "Duration Type": "output", "Start": 1601880385.852293, "End": 1601880385.8522968}, {"Model Name": "model3", "Model ID": 1, "Data Index": 0, "Request ID": 0, "Duration Type": "input", "Start": 1601880385.919198, "End": 1601880385.9192739}, {"Model Name": "model3", "Model ID": 1, "Data Index": 0, "Request ID": 0, "Duration Type": "infer", "Start": 1601880385.9192753, "End": 1601880385.9479768}, {"Model Name": "model3", "Model ID": 1, "Data Index": 0, "Request ID": 0, "Duration Type": "output", "Start": 1601880385.9479792, "End": 1601880385.9479825}, {"Model Name": "model3", "Model ID": 1, "Data Index": 0, "Request ID": 0, "Duration Type": "input", "Start": 1601880386.0144868, "End": 1601880386.014566}, {"Model Name": "model3", "Model ID": 1, "Data Index": 0, "Request ID": 0, "Duration Type": "infer", "Start": 1601880386.0145674, "End": 1601880386.0432992}, {"Model Name": "model3", "Model ID": 1, "Data Index": 0, "Request ID": 0, "Duration Type": "output", "Start": 1601880386.0433016, "End": 1601880386.0433047}, {"Model Name": "model3", "Model ID": 1, "Data Index": 0, "Request ID": 0, "Duration Type": "input", "Start": 1601880386.1121867, "End": 1601880386.1122646}, {"Model Name": "model3", "Model ID": 1, "Data Index": 0, "Request ID": 0, "Duration Type": "infer", "Start": 1601880386.112266, "End": 1601880386.1410856}, {"Model Name": "model3", "Model ID": 1, "Data Index": 0, "Request ID": 0, "Duration Type": "output", "Start": 1601880386.141088, "End": 1601880386.141091}, {"Model Name": "model3", "Model ID": 1, "Data Index": 0, "Request ID": 0, "Duration Type": "input", "Start": 1601880386.2088904, "End": 1601880386.2089672}, {"Model Name": "model3", "Model ID": 1, "Data Index": 0, "Request ID": 0, "Duration Type": "infer", "Start": 1601880386.2089686, "End": 1601880386.237801}, {"Model Name": "model3", "Model ID": 1, "Data Index": 0, "Request ID": 0, "Duration Type": "output", "Start": 1601880386.2378035, "End": 1601880386.2378068}, {"Model Name": "model3", "Model ID": 1, "Data Index": 0, "Request ID": 0, "Duration Type": "input", "Start": 1601880386.305155, "End": 1601880386.3052318}, {"Model Name": "model3", "Model ID": 1, "Data Index": 0, "Request ID": 0, "Duration Type": "infer", "Start": 1601880386.3052332, "End": 1601880386.3339343}, {"Model Name": "model3", "Model ID": 1, "Data Index": 0, "Request ID": 0, "Duration Type": "output", "Start": 1601880386.333937, "End": 1601880386.33394}, {"Model Name": "model3", "Model ID": 1, "Data Index": 0, "Request ID": 0, "Duration Type": "input", "Start": 1601880386.4005861, "End": 1601880386.4006631}, {"Model Name": "model3", "Model ID": 1, "Data Index": 0, "Request ID": 0, "Duration Type": "infer", "Start": 1601880386.4006646, "End": 1601880386.4294848}, {"Model Name": "model3", "Model ID": 1, "Data Index": 0, "Request ID": 0, "Duration Type": "output", "Start": 1601880386.4294872, "End": 1601880386.4294908}, {"Model Name": "model3", "Model ID": 1, "Data Index": 0, "Request ID": 0, "Duration Type": "input", "Start": 1601880386.4961276, "End": 1601880386.496206}, {"Model Name": "model3", "Model ID": 1, "Data Index": 0, "Request ID": 0, "Duration Type": "infer", "Start": 1601880386.4962075, "End": 1601880386.5249317}, {"Model Name": "model3", "Model ID": 1, "Data Index": 0, "Request ID": 0, "Duration Type": "output", "Start": 1601880386.5249343, "End": 1601880386.5249374}, {"Model Name": "model3", "Model ID": 1, "Data Index": 0, "Request ID": 0, "Duration Type": "input", "Start": 1601880386.5912938, "End": 1601880386.591371}, {"Model Name": "model3", "Model ID": 1, "Data Index": 0, "Request ID": 0, "Duration Type": "infer", "Start": 1601880386.5913723, "End": 1601880386.6200457}, {"Model Name": "model3", "Model ID": 1, "Data Index": 0, "Request ID": 0, "Duration Type": "output", "Start": 1601880386.620048, "End": 1601880386.6200514}, {"Model Name": "model3", "Model ID": 1, "Data Index": 0, "Request ID": 0, "Duration Type": "input", "Start": 1601880386.685011, "End": 1601880386.6850913}, {"Model Name": "model3", "Model ID": 1, "Data Index": 0, "Request ID": 0, "Duration Type": "infer", "Start": 1601880386.6850927, "End": 1601880386.7137103}, {"Model Name": "model3", "Model ID": 1, "Data Index": 0, "Request ID": 0, "Duration Type": "output", "Start": 1601880386.7137125, "End": 1601880386.7137156}, {"Model Name": "model3", "Model ID": 1, "Data Index": 0, "Request ID": 0, "Duration Type": "input", "Start": 1601880386.7760043, "End": 1601880386.7760818}, {"Model Name": "model3", "Model ID": 1, "Data Index": 0, "Request ID": 0, "Duration Type": "infer", "Start": 1601880386.7760832, "End": 1601880386.8048334}, {"Model Name": "model3", "Model ID": 1, "Data Index": 0, "Request ID": 0, "Duration Type": "output", "Start": 1601880386.8048358, "End": 1601880386.804839}, {"Model Name": "model3", "Model ID": 1, "Data Index": 0, "Request ID": 0, "Duration Type": "input", "Start": 1601880386.8734615, "End": 1601880386.8735383}, {"Model Name": "model3", "Model ID": 1, "Data Index": 0, "Request ID": 0, "Duration Type": "infer", "Start": 1601880386.8735397, "End": 1601880386.9022658}, {"Model Name": "model3", "Model ID": 1, "Data Index": 0, "Request ID": 0, "Duration Type": "output", "Start": 1601880386.9022677, "End": 1601880386.902271}, {"Model Name": "model3", "Model ID": 1, "Data Index": 0, "Request ID": 0, "Duration Type": "input", "Start": 1601880386.9698694, "End": 1601880386.9699488}, {"Model Name": "model3", "Model ID": 1, "Data Index": 0, "Request ID": 0, "Duration Type": "infer", "Start": 1601880386.9699502, "End": 1601880386.9985971}, {"Model Name": "model3", "Model ID": 1, "Data Index": 0, "Request ID": 0, "Duration Type": "output", "Start": 1601880386.9985995, "End": 1601880386.998603}, {"Model Name": "model3", "Model ID": 1, "Data Index": 0, "Request ID": 0, "Duration Type": "input", "Start": 1601880387.0656629, "End": 1601880387.065741}, {"Model Name": "model3", "Model ID": 1, "Data Index": 0, "Request ID": 0, "Duration Type": "infer", "Start": 1601880387.0657425, "End": 1601880387.0944397}, {"Model Name": "model3", "Model ID": 1, "Data Index": 0, "Request ID": 0, "Duration Type": "output", "Start": 1601880387.0944421, "End": 1601880387.0944455}, {"Model Name": "model3", "Model ID": 1, "Data Index": 0, "Request ID": 0, "Duration Type": "input", "Start": 1601880387.1634035, "End": 1601880387.1634808}, {"Model Name": "model3", "Model ID": 1, "Data Index": 0, "Request ID": 0, "Duration Type": "infer", "Start": 1601880387.163482, "End": 1601880387.1920965}, {"Model Name": "model3", "Model ID": 1, "Data Index": 0, "Request ID": 0, "Duration Type": "output", "Start": 1601880387.1920981, "End": 1601880387.1921015}, {"Model Name": "model3", "Model ID": 1, "Data Index": 0, "Request ID": 0, "Duration Type": "input", "Start": 1601880387.2615373, "End": 1601880387.2616158}, {"Model Name": "model3", "Model ID": 1, "Data Index": 0, "Request ID": 0, "Duration Type": "infer", "Start": 1601880387.2616172, "End": 1601880387.2902153}, {"Model Name": "model3", "Model ID": 1, "Data Index": 0, "Request ID": 0, "Duration Type": "output", "Start": 1601880387.2902174, "End": 1601880387.2902203}, {"Model Name": "model3", "Model ID": 1, "Data Index": 0, "Request ID": 0, "Duration Type": "input", "Start": 1601880387.358144, "End": 1601880387.3582194}, {"Model Name": "model3", "Model ID": 1, "Data Index": 0, "Request ID": 0, "Duration Type": "infer", "Start": 1601880387.3582208, "End": 1601880387.3869233}, {"Model Name": "model3", "Model ID": 1, "Data Index": 0, "Request ID": 0, "Duration Type": "output", "Start": 1601880387.3869255, "End": 1601880387.3869288}, {"Model Name": "model3", "Model ID": 1, "Data Index": 0, "Request ID": 0, "Duration Type": "input", "Start": 1601880387.4556847, "End": 1601880387.4557614}, {"Model Name": "model3", "Model ID": 1, "Data Index": 0, "Request ID": 0, "Duration Type": "infer", "Start": 1601880387.4557629, "End": 1601880387.484397}, {"Model Name": "model3", "Model ID": 1, "Data Index": 0, "Request ID": 0, "Duration Type": "output", "Start": 1601880387.4843988, "End": 1601880387.4844027}, {"Model Name": "model3", "Model ID": 1, "Data Index": 0, "Request ID": 0, "Duration Type": "input", "Start": 1601880387.5535264, "End": 1601880387.5536036}, {"Model Name": "model3", "Model ID": 1, "Data Index": 0, "Request ID": 0, "Duration Type": "infer", "Start": 1601880387.553605, "End": 1601880387.582309}, {"Model Name": "model3", "Model ID": 1, "Data Index": 0, "Request ID": 0, "Duration Type": "output", "Start": 1601880387.5823112, "End": 1601880387.582314}, {"Model Name": "model3", "Model ID": 1, "Data Index": 0, "Request ID": 0, "Duration Type": "input", "Start": 1601880387.6508474, "End": 1601880387.650921}, {"Model Name": "model3", "Model ID": 1, "Data Index": 0, "Request ID": 0, "Duration Type": "infer", "Start": 1601880387.6509225, "End": 1601880387.6796403}, {"Model Name": "model3", "Model ID": 1, "Data Index": 0, "Request ID": 0, "Duration Type": "output", "Start": 1601880387.6796424, "End": 1601880387.679646}, {"Model Name": "model3", "Model ID": 1, "Data Index": 0, "Request ID": 0, "Duration Type": "input", "Start": 1601880387.7474468, "End": 1601880387.7475233}, {"Model Name": "model3", "Model ID": 1, "Data Index": 0, "Request ID": 0, "Duration Type": "infer", "Start": 1601880387.7475247, "End": 1601880387.77614}, {"Model Name": "model3", "Model ID": 1, "Data Index": 0, "Request ID": 0, "Duration Type": "output", "Start": 1601880387.7761421, "End": 1601880387.776145}, {"Model Name": "model3", "Model ID": 1, "Data Index": 0, "Request ID": 0, "Duration Type": "input", "Start": 1601880387.8453524, "End": 1601880387.8454304}, {"Model Name": "model3", "Model ID": 1, "Data Index": 0, "Request ID": 0, "Duration Type": "infer", "Start": 1601880387.8454318, "End": 1601880387.8740406}, {"Model Name": "model3", "Model ID": 1, "Data Index": 0, "Request ID": 0, "Duration Type": "output", "Start": 1601880387.8740427, "End": 1601880387.8740456}, {"Model Name": "model3", "Model ID": 1, "Data Index": 0, "Request ID": 0, "Duration Type": "input", "Start": 1601880387.9418724, "End": 1601880387.9419515}, {"Model Name": "model3", "Model ID": 1, "Data Index": 0, "Request ID": 0, "Duration Type": "infer", "Start": 1601880387.941953, "End": 1601880387.9705968}, {"Model Name": "model3", "Model ID": 1, "Data Index": 0, "Request ID": 0, "Duration Type": "output", "Start": 1601880387.9705987, "End": 1601880387.9706018}, {"Model Name": "model3", "Model ID": 1, "Data Index": 0, "Request ID": 0, "Duration Type": "input", "Start": 1601880388.0374987, "End": 1601880388.0375767}, {"Model Name": "model3", "Model ID": 1, "Data Index": 0, "Request ID": 0, "Duration Type": "infer", "Start": 1601880388.037578, "End": 1601880388.066242}, {"Model Name": "model3", "Model ID": 1, "Data Index": 0, "Request ID": 0, "Duration Type": "output", "Start": 1601880388.0662441, "End": 1601880388.066247}, {"Model Name": "model3", "Model ID": 1, "Data Index": 0, "Request ID": 0, "Duration Type": "input", "Start": 1601880388.1336231, "End": 1601880388.1337008}, {"Model Name": "model3", "Model ID": 1, "Data Index": 0, "Request ID": 0, "Duration Type": "infer", "Start": 1601880388.1337023, "End": 1601880388.1624522}, {"Model Name": "model3", "Model ID": 1, "Data Index": 0, "Request ID": 0, "Duration Type": "output", "Start": 1601880388.1624544, "End": 1601880388.1624572}, {"Model Name": "model3", "Model ID": 1, "Data Index": 0, "Request ID": 0, "Duration Type": "input", "Start": 1601880388.2304742, "End": 1601880388.2305508}, {"Model Name": "model3", "Model ID": 1, "Data Index": 0, "Request ID": 0, "Duration Type": "infer", "Start": 1601880388.2305522, "End": 1601880388.2591398}, {"Model Name": "model3", "Model ID": 1, "Data Index": 0, "Request ID": 0, "Duration Type": "output", "Start": 1601880388.2591417, "End": 1601880388.2591448}, {"Model Name": "model3", "Model ID": 1, "Data Index": 0, "Request ID": 0, "Duration Type": "input", "Start": 1601880388.3282933, "End": 1601880388.3283715}, {"Model Name": "model3", "Model ID": 1, "Data Index": 0, "Request ID": 0, "Duration Type": "infer", "Start": 1601880388.328373, "End": 1601880388.3570125}, {"Model Name": "model3", "Model ID": 1, "Data Index": 0, "Request ID": 0, "Duration Type": "output", "Start": 1601880388.357015, "End": 1601880388.3570182}, {"Model Name": "model3", "Model ID": 1, "Data Index": 0, "Request ID": 0, "Duration Type": "input", "Start": 1601880388.424645, "End": 1601880388.4247239}, {"Model Name": "model3", "Model ID": 1, "Data Index": 0, "Request ID": 0, "Duration Type": "infer", "Start": 1601880388.4247253, "End": 1601880388.4534354}, {"Model Name": "model3", "Model ID": 1, "Data Index": 0, "Request ID": 0, "Duration Type": "output", "Start": 1601880388.4534376, "End": 1601880388.4534407}, {"Model Name": "model3", "Model ID": 1, "Data Index": 0, "Request ID": 0, "Duration Type": "input", "Start": 1601880388.5192637, "End": 1601880388.5193415}, {"Model Name": "model3", "Model ID": 1, "Data Index": 0, "Request ID": 0, "Duration Type": "infer", "Start": 1601880388.5193427, "End": 1601880388.5480447}, {"Model Name": "model3", "Model ID": 1, "Data Index": 0, "Request ID": 0, "Duration Type": "output", "Start": 1601880388.5480464, "End": 1601880388.5480494}, {"Model Name": "model3", "Model ID": 1, "Data Index": 0, "Request ID": 0, "Duration Type": "input", "Start": 1601880388.6164527, "End": 1601880388.6165304}, {"Model Name": "model3", "Model ID": 1, "Data Index": 0, "Request ID": 0, "Duration Type": "infer", "Start": 1601880388.6165318, "End": 1601880388.645205}, {"Model Name": "model3", "Model ID": 1, "Data Index": 0, "Request ID": 0, "Duration Type": "output", "Start": 1601880388.6452074, "End": 1601880388.645211}, {"Model Name": "model3", "Model ID": 1, "Data Index": 0, "Request ID": 0, "Duration Type": "input", "Start": 1601880388.711391, "End": 1601880388.7114682}, {"Model Name": "model3", "Model ID": 1, "Data Index": 0, "Request ID": 0, "Duration Type": "infer", "Start": 1601880388.7114694, "End": 1601880388.740127}, {"Model Name": "model3", "Model ID": 1, "Data Index": 0, "Request ID": 0, "Duration Type": "output", "Start": 1601880388.7401297, "End": 1601880388.7401323}, {"Model Name": "model3", "Model ID": 1, "Data Index": 0, "Request ID": 0, "Duration Type": "input", "Start": 1601880388.8065183, "End": 1601880388.8065953}, {"Model Name": "model3", "Model ID": 1, "Data Index": 0, "Request ID": 0, "Duration Type": "infer", "Start": 1601880388.8065968, "End": 1601880388.8352592}, {"Model Name": "model3", "Model ID": 1, "Data Index": 0, "Request ID": 0, "Duration Type": "output", "Start": 1601880388.8352613, "End": 1601880388.835265}, {"Model Name": "model3", "Model ID": 1, "Data Index": 0, "Request ID": 0, "Duration Type": "input", "Start": 1601880388.9021451, "End": 1601880388.902221}, {"Model Name": "model3", "Model ID": 1, "Data Index": 0, "Request ID": 0, "Duration Type": "infer", "Start": 1601880388.9022224, "End": 1601880388.9309158}, {"Model Name": "model3", "Model ID": 1, "Data Index": 0, "Request ID": 0, "Duration Type": "output", "Start": 1601880388.930918, "End": 1601880388.9309216}, {"Model Name": "model3", "Model ID": 1, "Data Index": 0, "Request ID": 0, "Duration Type": "input", "Start": 1601880388.999213, "End": 1601880388.999293}, {"Model Name": "model3", "Model ID": 1, "Data Index": 0, "Request ID": 0, "Duration Type": "infer", "Start": 1601880388.9992945, "End": 1601880389.0279884}, {"Model Name": "model3", "Model ID": 1, "Data Index": 0, "Request ID": 0, "Duration Type": "output", "Start": 1601880389.0279908, "End": 1601880389.027994}, {"Model Name": "model3", "Model ID": 1, "Data Index": 0, "Request ID": 0, "Duration Type": "input", "Start": 1601880389.328366, "End": 1601880389.3284426}, {"Model Name": "model3", "Model ID": 1, "Data Index": 0, "Request ID": 0, "Duration Type": "infer", "Start": 1601880389.328444, "End": 1601880389.3571358}, {"Model Name": "model3", "Model ID": 1, "Data Index": 0, "Request ID": 0, "Duration Type": "output", "Start": 1601880389.357138, "End": 1601880389.357141}, {"Model Name": "model3", "Model ID": 1, "Data Index": 0, "Request ID": 0, "Duration Type": "input", "Start": 1601880389.424826, "End": 1601880389.4249032}, {"Model Name": "model3", "Model ID": 1, "Data Index": 0, "Request ID": 0, "Duration Type": "infer", "Start": 1601880389.4249046, "End": 1601880389.4536073}, {"Model Name": "model3", "Model ID": 1, "Data Index": 0, "Request ID": 0, "Duration Type": "output", "Start": 1601880389.4536102, "End": 1601880389.4536133}, {"Model Name": "model3", "Model ID": 1, "Data Index": 0, "Request ID": 0, "Duration Type": "input", "Start": 1601880389.521518, "End": 1601880389.5215962}, {"Model Name": "model3", "Model ID": 1, "Data Index": 0, "Request ID": 0, "Duration Type": "infer", "Start": 1601880389.5215979, "End": 1601880389.5502687}, {"Model Name": "model3", "Model ID": 1, "Data Index": 0, "Request ID": 0, "Duration Type": "output", "Start": 1601880389.5502713, "End": 1601880389.5502746}, {"Model Name": "model3", "Model ID": 1, "Data Index": 0, "Request ID": 0, "Duration Type": "input", "Start": 1601880389.6168642, "End": 1601880389.6169417}, {"Model Name": "model3", "Model ID": 1, "Data Index": 0, "Request ID": 0, "Duration Type": "infer", "Start": 1601880389.6169431, "End": 1601880389.645706}, {"Model Name": "model3", "Model ID": 1, "Data Index": 0, "Request ID": 0, "Duration Type": "output", "Start": 1601880389.645708, "End": 1601880389.6457112}, {"Model Name": "model3", "Model ID": 1, "Data Index": 0, "Request ID": 0, "Duration Type": "input", "Start": 1601880389.712473, "End": 1601880389.7125483}, {"Model Name": "model3", "Model ID": 1, "Data Index": 0, "Request ID": 0, "Duration Type": "infer", "Start": 1601880389.7125497, "End": 1601880389.7412255}, {"Model Name": "model3", "Model ID": 1, "Data Index": 0, "Request ID": 0, "Duration Type": "output", "Start": 1601880389.7412276, "End": 1601880389.7412312}, {"Model Name": "model3", "Model ID": 1, "Data Index": 0, "Request ID": 0, "Duration Type": "input", "Start": 1601880389.8078995, "End": 1601880389.8079786}, {"Model Name": "model3", "Model ID": 1, "Data Index": 0, "Request ID": 0, "Duration Type": "infer", "Start": 1601880389.80798, "End": 1601880389.8366206}, {"Model Name": "model3", "Model ID": 1, "Data Index": 0, "Request ID": 0, "Duration Type": "output", "Start": 1601880389.836623, "End": 1601880389.8366265}, {"Model Name": "model3", "Model ID": 1, "Data Index": 0, "Request ID": 0, "Duration Type": "input", "Start": 1601880389.9028971, "End": 1601880389.9029727}, {"Model Name": "model3", "Model ID": 1, "Data Index": 0, "Request ID": 0, "Duration Type": "infer", "Start": 1601880389.9029741, "End": 1601880389.931658}, {"Model Name": "model3", "Model ID": 1, "Data Index": 0, "Request ID": 0, "Duration Type": "output", "Start": 1601880389.9316604, "End": 1601880389.9316642}, {"Model Name": "model3", "Model ID": 1, "Data Index": 0, "Request ID": 0, "Duration Type": "input", "Start": 1601880390.0010815, "End": 1601880390.0011582}, {"Model Name": "model3", "Model ID": 1, "Data Index": 0, "Request ID": 0, "Duration Type": "infer", "Start": 1601880390.0011594, "End": 1601880390.0299358}, {"Model Name": "model3", "Model ID": 1, "Data Index": 0, "Request ID": 0, "Duration Type": "output", "Start": 1601880390.0299382, "End": 1601880390.0299413}, {"Model Name": "model3", "Model ID": 1, "Data Index": 0, "Request ID": 0, "Duration Type": "input", "Start": 1601880390.1013129, "End": 1601880390.101391}, {"Model Name": "model3", "Model ID": 1, "Data Index": 0, "Request ID": 0, "Duration Type": "infer", "Start": 1601880390.1013925, "End": 1601880390.1300173}, {"Model Name": "model3", "Model ID": 1, "Data Index": 0, "Request ID": 0, "Duration Type": "output", "Start": 1601880390.13002, "End": 1601880390.1300228}, {"Model Name": "model3", "Model ID": 1, "Data Index": 0, "Request ID": 0, "Duration Type": "input", "Start": 1601880390.1984382, "End": 1601880390.1985168}, {"Model Name": "model3", "Model ID": 1, "Data Index": 0, "Request ID": 0, "Duration Type": "infer", "Start": 1601880390.1985183, "End": 1601880390.22712}, {"Model Name": "model3", "Model ID": 1, "Data Index": 0, "Request ID": 0, "Duration Type": "output", "Start": 1601880390.227122, "End": 1601880390.2271256}, {"Model Name": "model3", "Model ID": 1, "Data Index": 0, "Request ID": 0, "Duration Type": "input", "Start": 1601880390.2957196, "End": 1601880390.2957947}, {"Model Name": "model3", "Model ID": 1, "Data Index": 0, "Request ID": 0, "Duration Type": "infer", "Start": 1601880390.2957962, "End": 1601880390.3244605}, {"Model Name": "model3", "Model ID": 1, "Data Index": 0, "Request ID": 0, "Duration Type": "output", "Start": 1601880390.3244627, "End": 1601880390.3244658}, {"Model Name": "model3", "Model ID": 1, "Data Index": 0, "Request ID": 0, "Duration Type": "input", "Start": 1601880390.3933952, "End": 1601880390.393468}, {"Model Name": "model3", "Model ID": 1, "Data Index": 0, "Request ID": 0, "Duration Type": "infer", "Start": 1601880390.3934693, "End": 1601880390.422095}, {"Model Name": "model3", "Model ID": 1, "Data Index": 0, "Request ID": 0, "Duration Type": "output", "Start": 1601880390.4220974, "End": 1601880390.4221005}, {"Model Name": "model3", "Model ID": 1, "Data Index": 0, "Request ID": 0, "Duration Type": "input", "Start": 1601880390.4892666, "End": 1601880390.4893436}, {"Model Name": "model3", "Model ID": 1, "Data Index": 0, "Request ID": 0, "Duration Type": "infer", "Start": 1601880390.4893448, "End": 1601880390.5180242}, {"Model Name": "model3", "Model ID": 1, "Data Index": 0, "Request ID": 0, "Duration Type": "output", "Start": 1601880390.5180264, "End": 1601880390.5180302}, {"Model Name": "model3", "Model ID": 1, "Data Index": 0, "Request ID": 0, "Duration Type": "input", "Start": 1601880390.5858216, "End": 1601880390.5858986}, {"Model Name": "model3", "Model ID": 1, "Data Index": 0, "Request ID": 0, "Duration Type": "infer", "Start": 1601880390.5858998, "End": 1601880390.6145763}, {"Model Name": "model3", "Model ID": 1, "Data Index": 0, "Request ID": 0, "Duration Type": "output", "Start": 1601880390.614579, "End": 1601880390.6145825}, {"Model Name": "model3", "Model ID": 1, "Data Index": 0, "Request ID": 0, "Duration Type": "input", "Start": 1601880390.6824045, "End": 1601880390.682481}, {"Model Name": "model3", "Model ID": 1, "Data Index": 0, "Request ID": 0, "Duration Type": "infer", "Start": 1601880390.6824825, "End": 1601880390.7111392}, {"Model Name": "model3", "Model ID": 1, "Data Index": 0, "Request ID": 0, "Duration Type": "output", "Start": 1601880390.7111416, "End": 1601880390.711145}, {"Model Name": "model3", "Model ID": 1, "Data Index": 0, "Request ID": 0, "Duration Type": "input", "Start": 1601880390.7783852, "End": 1601880390.7784605}, {"Model Name": "model3", "Model ID": 1, "Data Index": 0, "Request ID": 0, "Duration Type": "infer", "Start": 1601880390.778462, "End": 1601880390.8071282}, {"Model Name": "model3", "Model ID": 1, "Data Index": 0, "Request ID": 0, "Duration Type": "output", "Start": 1601880390.8071303, "End": 1601880390.8071337}, {"Model Name": "model3", "Model ID": 1, "Data Index": 0, "Request ID": 0, "Duration Type": "input", "Start": 1601880390.8726172, "End": 1601880390.8726969}, {"Model Name": "model3", "Model ID": 1, "Data Index": 0, "Request ID": 0, "Duration Type": "infer", "Start": 1601880390.872698, "End": 1601880390.9013596}, {"Model Name": "model3", "Model ID": 1, "Data Index": 0, "Request ID": 0, "Duration Type": "output", "Start": 1601880390.9013622, "End": 1601880390.9013658}, {"Model Name": "model3", "Model ID": 1, "Data Index": 0, "Request ID": 0, "Duration Type": "input", "Start": 1601880390.969305, "End": 1601880390.9693828}, {"Model Name": "model3", "Model ID": 1, "Data Index": 0, "Request ID": 0, "Duration Type": "infer", "Start": 1601880390.9693842, "End": 1601880390.9979928}, {"Model Name": "model3", "Model ID": 1, "Data Index": 0, "Request ID": 0, "Duration Type": "output", "Start": 1601880390.997995, "End": 1601880390.9979987}, {"Model Name": "model3", "Model ID": 1, "Data Index": 0, "Request ID": 0, "Duration Type": "input", "Start": 1601880391.0687754, "End": 1601880391.0688505}, {"Model Name": "model3", "Model ID": 1, "Data Index": 0, "Request ID": 0, "Duration Type": "infer", "Start": 1601880391.0688517, "End": 1601880391.0975955}, {"Model Name": "model3", "Model ID": 1, "Data Index": 0, "Request ID": 0, "Duration Type": "output", "Start": 1601880391.0975976, "End": 1601880391.0976012}, {"Model Name": "model3", "Model ID": 1, "Data Index": 0, "Request ID": 0, "Duration Type": "input", "Start": 1601880391.16727, "End": 1601880391.1673465}, {"Model Name": "model3", "Model ID": 1, "Data Index": 0, "Request ID": 0, "Duration Type": "infer", "Start": 1601880391.167348, "End": 1601880391.1959374}, {"Model Name": "model3", "Model ID": 1, "Data Index": 0, "Request ID": 0, "Duration Type": "output", "Start": 1601880391.1959398, "End": 1601880391.1959436}, {"Model Name": "model3", "Model ID": 1, "Data Index": 0, "Request ID": 0, "Duration Type": "input", "Start": 1601880391.2632327, "End": 1601880391.2633111}, {"Model Name": "model3", "Model ID": 1, "Data Index": 0, "Request ID": 0, "Duration Type": "infer", "Start": 1601880391.2633123, "End": 1601880391.291944}, {"Model Name": "model3", "Model ID": 1, "Data Index": 0, "Request ID": 0, "Duration Type": "output", "Start": 1601880391.2919464, "End": 1601880391.2919495}, {"Model Name": "model3", "Model ID": 1, "Data Index": 0, "Request ID": 0, "Duration Type": "input", "Start": 1601880391.3607821, "End": 1601880391.3608592}, {"Model Name": "model3", "Model ID": 1, "Data Index": 0, "Request ID": 0, "Duration Type": "infer", "Start": 1601880391.3608608, "End": 1601880391.3895452}, {"Model Name": "model3", "Model ID": 1, "Data Index": 0, "Request ID": 0, "Duration Type": "output", "Start": 1601880391.3895476, "End": 1601880391.3895514}, {"Model Name": "model3", "Model ID": 1, "Data Index": 0, "Request ID": 0, "Duration Type": "input", "Start": 1601880391.4618313, "End": 1601880391.4619088}, {"Model Name": "model3", "Model ID": 1, "Data Index": 0, "Request ID": 0, "Duration Type": "infer", "Start": 1601880391.4619102, "End": 1601880391.4905853}, {"Model Name": "model3", "Model ID": 1, "Data Index": 0, "Request ID": 0, "Duration Type": "output", "Start": 1601880391.4905875, "End": 1601880391.4905915}, {"Model Name": "model3", "Model ID": 1, "Data Index": 0, "Request ID": 0, "Duration Type": "input", "Start": 1601880391.5552623, "End": 1601880391.555341}, {"Model Name": "model3", "Model ID": 1, "Data Index": 0, "Request ID": 0, "Duration Type": "infer", "Start": 1601880391.5553424, "End": 1601880391.5846233}, {"Model Name": "model3", "Model ID": 1, "Data Index": 0, "Request ID": 0, "Duration Type": "output", "Start": 1601880391.5846252, "End": 1601880391.5846286}, {"Model Name": "model3", "Model ID": 1, "Data Index": 0, "Request ID": 0, "Duration Type": "input", "Start": 1601880391.6544192, "End": 1601880391.6544924}, {"Model Name": "model3", "Model ID": 1, "Data Index": 0, "Request ID": 0, "Duration Type": "infer", "Start": 1601880391.6544938, "End": 1601880391.6832278}, {"Model Name": "model3", "Model ID": 1, "Data Index": 0, "Request ID": 0, "Duration Type": "output", "Start": 1601880391.68323, "End": 1601880391.6832335}, {"Model Name": "model3", "Model ID": 1, "Data Index": 0, "Request ID": 0, "Duration Type": "input", "Start": 1601880391.749613, "End": 1601880391.7496893}, {"Model Name": "model3", "Model ID": 1, "Data Index": 0, "Request ID": 0, "Duration Type": "infer", "Start": 1601880391.7496908, "End": 1601880391.778404}, {"Model Name": "model3", "Model ID": 1, "Data Index": 0, "Request ID": 0, "Duration Type": "output", "Start": 1601880391.7784061, "End": 1601880391.7784092}, {"Model Name": "model3", "Model ID": 1, "Data Index": 0, "Request ID": 0, "Duration Type": "input", "Start": 1601880391.8450654, "End": 1601880391.8451428}, {"Model Name": "model3", "Model ID": 1, "Data Index": 0, "Request ID": 0, "Duration Type": "infer", "Start": 1601880391.8451443, "End": 1601880391.8738623}, {"Model Name": "model3", "Model ID": 1, "Data Index": 0, "Request ID": 0, "Duration Type": "output", "Start": 1601880391.8738647, "End": 1601880391.8738682}, {"Model Name": "model3", "Model ID": 1, "Data Index": 0, "Request ID": 0, "Duration Type": "input", "Start": 1601880391.942299, "End": 1601880391.9423778}, {"Model Name": "model3", "Model ID": 1, "Data Index": 0, "Request ID": 0, "Duration Type": "infer", "Start": 1601880391.9423792, "End": 1601880391.9710119}, {"Model Name": "model3", "Model ID": 1, "Data Index": 0, "Request ID": 0, "Duration Type": "output", "Start": 1601880391.9710147, "End": 1601880391.9710178}, {"Model Name": "model3", "Model ID": 1, "Data Index": 0, "Request ID": 0, "Duration Type": "input", "Start": 1601880392.0399814, "End": 1601880392.0400584}, {"Model Name": "model3", "Model ID": 1, "Data Index": 0, "Request ID": 0, "Duration Type": "infer", "Start": 1601880392.0400598, "End": 1601880392.0686884}, {"Model Name": "model3", "Model ID": 1, "Data Index": 0, "Request ID": 0, "Duration Type": "output", "Start": 1601880392.0686903, "End": 1601880392.0686936}, {"Model Name": "model3", "Model ID": 1, "Data Index": 0, "Request ID": 0, "Duration Type": "input", "Start": 1601880392.136917, "End": 1601880392.1369941}, {"Model Name": "model3", "Model ID": 1, "Data Index": 0, "Request ID": 0, "Duration Type": "infer", "Start": 1601880392.1369956, "End": 1601880392.1656616}, {"Model Name": "model3", "Model ID": 1, "Data Index": 0, "Request ID": 0, "Duration Type": "output", "Start": 1601880392.165664, "End": 1601880392.165667}, {"Model Name": "model3", "Model ID": 1, "Data Index": 0, "Request ID": 0, "Duration Type": "input", "Start": 1601880392.2325675, "End": 1601880392.2326438}, {"Model Name": "model3", "Model ID": 1, "Data Index": 0, "Request ID": 0, "Duration Type": "infer", "Start": 1601880392.2326453, "End": 1601880392.2612987}, {"Model Name": "model3", "Model ID": 1, "Data Index": 0, "Request ID": 0, "Duration Type": "output", "Start": 1601880392.261301, "End": 1601880392.261304}, {"Model Name": "model3", "Model ID": 1, "Data Index": 0, "Request ID": 0, "Duration Type": "input", "Start": 1601880392.3276474, "End": 1601880392.3277242}, {"Model Name": "model3", "Model ID": 1, "Data Index": 0, "Request ID": 0, "Duration Type": "infer", "Start": 1601880392.3277254, "End": 1601880392.3564272}, {"Model Name": "model3", "Model ID": 1, "Data Index": 0, "Request ID": 0, "Duration Type": "output", "Start": 1601880392.3564296, "End": 1601880392.3564324}, {"Model Name": "model3", "Model ID": 1, "Data Index": 0, "Request ID": 0, "Duration Type": "input", "Start": 1601880392.424601, "End": 1601880392.4246776}, {"Model Name": "model3", "Model ID": 1, "Data Index": 0, "Request ID": 0, "Duration Type": "infer", "Start": 1601880392.4246788, "End": 1601880392.4533637}, {"Model Name": "model3", "Model ID": 1, "Data Index": 0, "Request ID": 0, "Duration Type": "output", "Start": 1601880392.453366, "End": 1601880392.453369}, {"Model Name": "model3", "Model ID": 1, "Data Index": 0, "Request ID": 0, "Duration Type": "input", "Start": 1601880392.5186505, "End": 1601880392.5187287}, {"Model Name": "model3", "Model ID": 1, "Data Index": 0, "Request ID": 0, "Duration Type": "infer", "Start": 1601880392.5187302, "End": 1601880392.54732}, {"Model Name": "model3", "Model ID": 1, "Data Index": 0, "Request ID": 0, "Duration Type": "output", "Start": 1601880392.5473225, "End": 1601880392.5473256}, {"Model Name": "model3", "Model ID": 1, "Data Index": 0, "Request ID": 0, "Duration Type": "input", "Start": 1601880392.6158538, "End": 1601880392.6159322}, {"Model Name": "model3", "Model ID": 1, "Data Index": 0, "Request ID": 0, "Duration Type": "infer", "Start": 1601880392.6159334, "End": 1601880392.6445959}, {"Model Name": "model3", "Model ID": 1, "Data Index": 0, "Request ID": 0, "Duration Type": "output", "Start": 1601880392.6445987, "End": 1601880392.6446018}, {"Model Name": "model3", "Model ID": 1, "Data Index": 0, "Request ID": 0, "Duration Type": "input", "Start": 1601880392.713814, "End": 1601880392.7138906}, {"Model Name": "model3", "Model ID": 1, "Data Index": 0, "Request ID": 0, "Duration Type": "infer", "Start": 1601880392.7138917, "End": 1601880392.7426102}, {"Model Name": "model3", "Model ID": 1, "Data Index": 0, "Request ID": 0, "Duration Type": "output", "Start": 1601880392.742613, "End": 1601880392.7426164}, {"Model Name": "model3", "Model ID": 1, "Data Index": 0, "Request ID": 0, "Duration Type": "input", "Start": 1601880392.810846, "End": 1601880392.810924}, {"Model Name": "model3", "Model ID": 1, "Data Index": 0, "Request ID": 0, "Duration Type": "infer", "Start": 1601880392.8109255, "End": 1601880392.839681}, {"Model Name": "model3", "Model ID": 1, "Data Index": 0, "Request ID": 0, "Duration Type": "output", "Start": 1601880392.8396828, "End": 1601880392.839686}]}}
